{
  "generator-jhipster": {
    "applicationType": "monolith",
    "gitCompany": "",
    "baseName": "GestionStockJhipster",
    "packageName": "com.mycompany.myapp",
    "packageFolder": "com/mycompany/myapp",
    "serverPort": 8080,
    "serviceDiscoveryType": false,
    "authenticationType": "jwt",
    "uaaBaseName": "../uaa",
    "cacheProvider": "ehcache",
    "enableHibernateCache": true,
    "websocket": false,
    "databaseType": "sql",
    "devDatabaseType": "postgresql",
    "prodDatabaseType": "postgresql",
    "searchEngine": false,
    "enableSwaggerCodegen": false,
    "messageBroker": false,
    "buildTool": "maven",
    "useSass": true,
    "clientPackageManager": "npm",
    "testFrameworks": [],
    "enableTranslation": true,
    "nativeLanguage": "fr",
    "languages": ["en", "fr"],
    "clientFramework": "angularX",
    "jhiPrefix": "jhi",
    "jhipsterVersion": "6.10.5",
    "jwtSecretKey": "YmJiYzFlYThkZTgxNDA3MTQxNmEzZjNmODJkMzA1ZWE2OTcxYjY5ZWRkNDNmZTVhMGFlZGY0NjNjMDNmYjBjZDgyOGJhNjIxZWE2MTJlOTc1MmQyMzhkY2M4YzUzMzg5MTFmMjMwNTRlZDRjN2Q2MzAzZjFiZWY3YWIxYWIwNTQ=",
    "embeddableLaunchScript": false,
    "clientTheme": "none",
    "creationTimestamp": 1614259582017,
    "entitySuffix": "",
    "dtoSuffix": "DTO",
    "otherModules": [],
    "blueprints": [],
    "prettierJava": true
  },
  "git-provider": "GitHub",
  "git-company": "hayadi",
  "repository-name": "GestionStockJhipster"
}
